wa_cloud_py/__init__.py
wa_cloud_py/verticals.py
wa_cloud_py/whatsapp.py
wa_cloud_py/components/__init__.py
wa_cloud_py/components/conversational.py
wa_cloud_py/components/messages.py
wa_cloud_py/messages/__init__.py
wa_cloud_py/messages/types.py
wa_cloud_py-0.1.6.dist-info/LICENSE.txt
wa_cloud_py-0.1.6.dist-info/METADATA
wa_cloud_py-0.1.6.dist-info/WHEEL
wa_cloud_py-0.1.6.dist-info/top_level.txt
wa_cloud_py-0.1.6.dist-info/RECORD
